ntheory/__init__.py
ntheory/binary/__init__.py
ntheory/binary/utils.py
ntheory/core/__init__.py
ntheory/core/tmp.py
ntheory/modulo/__init__.py
ntheory/modulo/modular_arithmetic.py
ntheory/primes/__init__.py
ntheory/primes/factors.py
ntheory/primes/primes_range.py
tests/__init__.py
tests/test_modulo/__init__.py
tests/test_modulo/test_modular_arithmetic.py
tests/test_primes/__init__.py
tests/test_primes/test_factors.py
ntheory-0.0.9.dist-info/LICENSE
ntheory-0.0.9.dist-info/METADATA
ntheory-0.0.9.dist-info/WHEEL
ntheory-0.0.9.dist-info/entry_points.txt
ntheory-0.0.9.dist-info/top_level.txt
ntheory-0.0.9.dist-info/RECORD
