Metadata-Version: 2.1
Name: ntheory
Version: 0.0.9
Summary: Read the latest Real Python tutorials
Author: Kasper Arfman
Author-email: KasperArfman <kasper.arf@gmail.com>
License: MIT License
Project-URL: Homepage, https://github.com/Kasper-Arfman/ntheory
Keywords: feed,reader,tutorial
Classifier: License :: OSI Approved :: MIT License
Classifier: Programming Language :: Python
Classifier: Programming Language :: Python :: 3
Requires-Python: >=3.9
License-File: LICENSE
Requires-Dist: feedparser (>=5.2.0)
Requires-Dist: html2text
Requires-Dist: numpy (>=1.24.3)
Requires-Dist: tomli ; python_version < "3.11"
Provides-Extra: dev
Requires-Dist: black ; extra == 'dev'
Requires-Dist: bumpver ; extra == 'dev'
Requires-Dist: isort ; extra == 'dev'
Requires-Dist: pip-tools ; extra == 'dev'
Requires-Dist: pytest ; extra == 'dev'
